README.rst
setup.py
wilfred.py
wilfred_say.egg-info/PKG-INFO
wilfred_say.egg-info/SOURCES.txt
wilfred_say.egg-info/dependency_links.txt
wilfred_say.egg-info/entry_points.txt
wilfred_say.egg-info/top_level.txt