Metadata-Version: 1.0
Name: wilfred-say
Version: 3.0
Summary: Print Wilfred quotes to the commandline
Home-page: http://github.com/arecker/wilfred-say
Author: Alex Recker
Author-email: alex@reckerfamily.com
License: GPLv3
Keywords: wilfred quotes commandline
Platform: UNKNOWN
